Metadata-Version: 2.1
Name: pyDbOracle
Version: 0.3
Summary: Standard Oracle Using (queries, updates, inserts)
Home-page: https://github.com/wgalleti/pyDbOracle
Author: William Galleti
Author-email: william.galleti@gmail.com
License: BSD
Platform: UNKNOWN
Classifier: Development Status :: 4 - Beta
Classifier: Environment :: Console
Classifier: Intended Audience :: Developers
Classifier: License :: OSI Approved :: BSD License
Classifier: Operating System :: OS Independent
Classifier: Programming Language :: Python :: 3.6
Classifier: Framework :: Pytest
